mcp_cuc_pbw/__init__.py
mcp_cuc_pbw/mcp_server.py
mcp_cuc_pbw-0.1.2.dist-info/licenses/LICENSE
mcp_cuc_pbw-0.1.2.dist-info/METADATA
mcp_cuc_pbw-0.1.2.dist-info/WHEEL
mcp_cuc_pbw-0.1.2.dist-info/entry_points.txt
mcp_cuc_pbw-0.1.2.dist-info/top_level.txt
mcp_cuc_pbw-0.1.2.dist-info/RECORD
